setup.py
PyRoomba.egg-info/PKG-INFO
PyRoomba.egg-info/SOURCES.txt
PyRoomba.egg-info/dependency_links.txt
PyRoomba.egg-info/top_level.txt
roomba/__init__.py
roomba/controllers.py
roomba/roomba.py
roomba/sensors/__init__.py
roomba/sensors/create_sensors.py
roomba/sensors/roomba_sensors.py