Metadata-Version: 1.1
Name: PyRoomba
Version: 0.1.0
Summary: UNKNOWN
Home-page: UNKNOWN
Author: Marcell Vazquez-Chanlatte
Author-email: UNKNOWN
License: LICENSE
Platform: UNKNOWN
Requires: amqp
Requires: pyserial
